{"nodes": [{"id": "users_alex_documents_08_mycrew_anti_03_reference_ip_05_dual_model_insights_v1_cks_\uc5f0\uad6c\ud504\ub808\uc784\uc6cc\ud06c_\uc5f0\uad6c\uacc4\ud68d\uc11c_\uac80\ud1a0\uc758\uacac_sonnet_md", "label": "\uac80\ud1a0\uc758\uacac_Sonnet.md", "file_type": "document", "source_file": "/Users/alex/Documents/08_MyCrew_Anti/03_Reference_IP/05_Dual-Model_Insights_v1/\ud83d\udd2c CKS_\uc5f0\uad6c\ud504\ub808\uc784\uc6cc\ud06c/\uc5f0\uad6c\uacc4\ud68d\uc11c/\uac80\ud1a0\uc758\uacac_Sonnet.md", "source_location": "L1"}, {"id": "\uc5f0\uad6c\uacc4\ud68d\uc11c_\uac80\ud1a0\uc758\uacac_sonnet_\uc5f0\uad6c\uacc4\ud68d\uc11c_\uac80\ud1a0_\uc758\uacac", "label": "\uc5f0\uad6c\uacc4\ud68d\uc11c \uac80\ud1a0 \uc758\uacac", "file_type": "document", "source_file": "/Users/alex/Documents/08_MyCrew_Anti/03_Reference_IP/05_Dual-Model_Insights_v1/\ud83d\udd2c CKS_\uc5f0\uad6c\ud504\ub808\uc784\uc6cc\ud06c/\uc5f0\uad6c\uacc4\ud68d\uc11c/\uac80\ud1a0\uc758\uacac_Sonnet.md", "source_location": "L1"}, {"id": "\uc5f0\uad6c\uacc4\ud68d\uc11c_\uac80\ud1a0\uc758\uacac_sonnet_\uc18c\ub137\uc758_\ub300\ud45c\ub2d8_\uc5f0\uad6c\uacc4\ud68d\uc11c_\ub9ac\ubdf0", "label": "\uc18c\ub137\uc758 \ub300\ud45c\ub2d8 \uc5f0\uad6c\uacc4\ud68d\uc11c \ub9ac\ubdf0", "file_type": "document", "source_file": "/Users/alex/Documents/08_MyCrew_Anti/03_Reference_IP/05_Dual-Model_Insights_v1/\ud83d\udd2c CKS_\uc5f0\uad6c\ud504\ub808\uc784\uc6cc\ud06c/\uc5f0\uad6c\uacc4\ud68d\uc11c/\uac80\ud1a0\uc758\uacac_Sonnet.md", "source_location": "L2"}, {"id": "\uc5f0\uad6c\uacc4\ud68d\uc11c_\uac80\ud1a0\uc758\uacac_sonnet_\uc798_\ub41c_\ubd80\ubd84", "label": "\u2705 \uc798 \ub41c \ubd80\ubd84", "file_type": "document", "source_file": "/Users/alex/Documents/08_MyCrew_Anti/03_Reference_IP/05_Dual-Model_Insights_v1/\ud83d\udd2c CKS_\uc5f0\uad6c\ud504\ub808\uc784\uc6cc\ud06c/\uc5f0\uad6c\uacc4\ud68d\uc11c/\uac80\ud1a0\uc758\uacac_Sonnet.md", "source_location": "L11"}, {"id": "\uc5f0\uad6c\uacc4\ud68d\uc11c_\uac80\ud1a0\uc758\uacac_sonnet_\uc218\uc815_\ud544\uc218_\uce58\uba85\uc801_\ubb38\uc81c_3\uac1c", "label": "\ud83d\udd34 \uc218\uc815 \ud544\uc218 \u2014 \uce58\uba85\uc801 \ubb38\uc81c (3\uac1c)", "file_type": "document", "source_file": "/Users/alex/Documents/08_MyCrew_Anti/03_Reference_IP/05_Dual-Model_Insights_v1/\ud83d\udd2c CKS_\uc5f0\uad6c\ud504\ub808\uc784\uc6cc\ud06c/\uc5f0\uad6c\uacc4\ud68d\uc11c/\uac80\ud1a0\uc758\uacac_Sonnet.md", "source_location": "L19"}, {"id": "\uc5f0\uad6c\uacc4\ud68d\uc11c_\uac80\ud1a0\uc758\uacac_sonnet_1_\ud3c9\uac00\uc790_\uc21c\ud658_\ud3b8\ud5a5_circular_bias", "label": "\u2460 \ud3c9\uac00\uc790 \uc21c\ud658 \ud3b8\ud5a5 (Circular Bias)", "file_type": "document", "source_file": "/Users/alex/Documents/08_MyCrew_Anti/03_Reference_IP/05_Dual-Model_Insights_v1/\ud83d\udd2c CKS_\uc5f0\uad6c\ud504\ub808\uc784\uc6cc\ud06c/\uc5f0\uad6c\uacc4\ud68d\uc11c/\uac80\ud1a0\uc758\uacac_Sonnet.md", "source_location": "L23"}, {"id": "\uc5f0\uad6c\uacc4\ud68d\uc11c_\uac80\ud1a0\uc758\uacac_sonnet_codeblock_1", "label": "code:block1 (\ubb38\uc81c:)", "file_type": "document", "source_file": "/Users/alex/Documents/08_MyCrew_Anti/03_Reference_IP/05_Dual-Model_Insights_v1/\ud83d\udd2c CKS_\uc5f0\uad6c\ud504\ub808\uc784\uc6cc\ud06c/\uc5f0\uad6c\uacc4\ud68d\uc11c/\uac80\ud1a0\uc758\uacac_Sonnet.md", "source_location": "L27"}, {"id": "\uc5f0\uad6c\uacc4\ud68d\uc11c_\uac80\ud1a0\uc758\uacac_sonnet_2_phase_4_\uba54\ud0c0_\ud504\ub86c\ud504\ud305\uc758_\uc624\uc5fc_\uac00\ub2a5\uc131_\ubbf8\uc124\uba85", "label": "\u2461 Phase 4 \uba54\ud0c0 \ud504\ub86c\ud504\ud305\uc758 \uc624\uc5fc \uac00\ub2a5\uc131 \ubbf8\uc124\uba85", "file_type": "document", "source_file": "/Users/alex/Documents/08_MyCrew_Anti/03_Reference_IP/05_Dual-Model_Insights_v1/\ud83d\udd2c CKS_\uc5f0\uad6c\ud504\ub808\uc784\uc6cc\ud06c/\uc5f0\uad6c\uacc4\ud68d\uc11c/\uac80\ud1a0\uc758\uacac_Sonnet.md", "source_location": "L40"}, {"id": "\uc5f0\uad6c\uacc4\ud68d\uc11c_\uac80\ud1a0\uc758\uacac_sonnet_codeblock_2", "label": "code:block2 (\uc608\uc0c1 \uc2ec\uc0ac\uc704\uc6d0 \uc9c8\ubb38:)", "file_type": "document", "source_file": "/Users/alex/Documents/08_MyCrew_Anti/03_Reference_IP/05_Dual-Model_Insights_v1/\ud83d\udd2c CKS_\uc5f0\uad6c\ud504\ub808\uc784\uc6cc\ud06c/\uc5f0\uad6c\uacc4\ud68d\uc11c/\uac80\ud1a0\uc758\uacac_Sonnet.md", "source_location": "L44"}, {"id": "\uc5f0\uad6c\uacc4\ud68d\uc11c_\uac80\ud1a0\uc758\uacac_sonnet_3_ksi_\uacf5\uc2dd_\ubbf8\uc815\uc758", "label": "\u2462 KSI \uacf5\uc2dd \ubbf8\uc815\uc758", "file_type": "document", "source_file": "/Users/alex/Documents/08_MyCrew_Anti/03_Reference_IP/05_Dual-Model_Insights_v1/\ud83d\udd2c CKS_\uc5f0\uad6c\ud504\ub808\uc784\uc6cc\ud06c/\uc5f0\uad6c\uacc4\ud68d\uc11c/\uac80\ud1a0\uc758\uacac_Sonnet.md", "source_location": "L56"}, {"id": "\uc5f0\uad6c\uacc4\ud68d\uc11c_\uac80\ud1a0\uc758\uacac_sonnet_codeblock_3", "label": "code:block3 (KSI = ( f(B\u2192A) + f(A\u2192B) ) \u00f7 2)", "file_type": "document", "source_file": "/Users/alex/Documents/08_MyCrew_Anti/03_Reference_IP/05_Dual-Model_Insights_v1/\ud83d\udd2c CKS_\uc5f0\uad6c\ud504\ub808\uc784\uc6cc\ud06c/\uc5f0\uad6c\uacc4\ud68d\uc11c/\uac80\ud1a0\uc758\uacac_Sonnet.md", "source_location": "L61"}, {"id": "\uc5f0\uad6c\uacc4\ud68d\uc11c_\uac80\ud1a0\uc758\uacac_sonnet_\ubcf4\uc644_\uad8c\uc7a5_4\uac1c", "label": "\ud83d\udfe1 \ubcf4\uc644 \uad8c\uc7a5 (4\uac1c)", "file_type": "document", "source_file": "/Users/alex/Documents/08_MyCrew_Anti/03_Reference_IP/05_Dual-Model_Insights_v1/\ud83d\udd2c CKS_\uc5f0\uad6c\ud504\ub808\uc784\uc6cc\ud06c/\uc5f0\uad6c\uacc4\ud68d\uc11c/\uac80\ud1a0\uc758\uacac_Sonnet.md", "source_location": "L73"}, {"id": "\uc5f0\uad6c\uacc4\ud68d\uc11c_\uac80\ud1a0\uc758\uacac_sonnet_4_research_question_rq_\ubd80\uc7ac", "label": "\u2463 Research Question (RQ) \ubd80\uc7ac", "file_type": "document", "source_file": "/Users/alex/Documents/08_MyCrew_Anti/03_Reference_IP/05_Dual-Model_Insights_v1/\ud83d\udd2c CKS_\uc5f0\uad6c\ud504\ub808\uc784\uc6cc\ud06c/\uc5f0\uad6c\uacc4\ud68d\uc11c/\uac80\ud1a0\uc758\uacac_Sonnet.md", "source_location": "L75"}, {"id": "\uc5f0\uad6c\uacc4\ud68d\uc11c_\uac80\ud1a0\uc758\uacac_sonnet_codeblock_4", "label": "code:block4 (RQ1: CKS \ud504\ub808\uc784\uc6cc\ud06c\ub294 \uc801\ub300\uc801 \ud504\ub808\uc784\uc6cc\ud06c \ub300\ube44)", "file_type": "document", "source_file": "/Users/alex/Documents/08_MyCrew_Anti/03_Reference_IP/05_Dual-Model_Insights_v1/\ud83d\udd2c CKS_\uc5f0\uad6c\ud504\ub808\uc784\uc6cc\ud06c/\uc5f0\uad6c\uacc4\ud68d\uc11c/\uac80\ud1a0\uc758\uacac_Sonnet.md", "source_location": "L80"}, {"id": "\uc5f0\uad6c\uacc4\ud68d\uc11c_\uac80\ud1a0\uc758\uacac_sonnet_5_\uad00\ub828_\uc5f0\uad6c_related_work_\uc804\ubb34", "label": "\u2464 \uad00\ub828 \uc5f0\uad6c(Related Work) \uc804\ubb34", "file_type": "document", "source_file": "/Users/alex/Documents/08_MyCrew_Anti/03_Reference_IP/05_Dual-Model_Insights_v1/\ud83d\udd2c CKS_\uc5f0\uad6c\ud504\ub808\uc784\uc6cc\ud06c/\uc5f0\uad6c\uacc4\ud68d\uc11c/\uac80\ud1a0\uc758\uacac_Sonnet.md", "source_location": "L93"}, {"id": "\uc5f0\uad6c\uacc4\ud68d\uc11c_\uac80\ud1a0\uc758\uacac_sonnet_6_\ud30c\uc77c\ub7ff_\ub370\uc774\ud130_\ubbf8\uc5b8\uae09", "label": "\u2465 \ud30c\uc77c\ub7ff \ub370\uc774\ud130 \ubbf8\uc5b8\uae09", "file_type": "document", "source_file": "/Users/alex/Documents/08_MyCrew_Anti/03_Reference_IP/05_Dual-Model_Insights_v1/\ud83d\udd2c CKS_\uc5f0\uad6c\ud504\ub808\uc784\uc6cc\ud06c/\uc5f0\uad6c\uacc4\ud68d\uc11c/\uac80\ud1a0\uc758\uacac_Sonnet.md", "source_location": "L105"}, {"id": "\uc5f0\uad6c\uacc4\ud68d\uc11c_\uac80\ud1a0\uc758\uacac_sonnet_codeblock_5", "label": "code:block5 (EII = 3\uac1c \ucc3d\ubc1c \uc544\uc774\ub514\uc5b4 (\ub2e8\uc77c \uc5d0\uc774\uc804\ud2b8 \ucd9c\ub825\uc5d0 \ubbf8\uc874\uc7ac))", "file_type": "document", "source_file": "/Users/alex/Documents/08_MyCrew_Anti/03_Reference_IP/05_Dual-Model_Insights_v1/\ud83d\udd2c CKS_\uc5f0\uad6c\ud504\ub808\uc784\uc6cc\ud06c/\uc5f0\uad6c\uacc4\ud68d\uc11c/\uac80\ud1a0\uc758\uacac_Sonnet.md", "source_location": "L108"}, {"id": "\uc5f0\uad6c\uacc4\ud68d\uc11c_\uac80\ud1a0\uc758\uacac_sonnet_7_\ud55c\uacc4\uc810_\ucd94\uac00_\ud544\uc694", "label": "\u2466 \ud55c\uacc4\uc810 \ucd94\uac00 \ud544\uc694", "file_type": "document", "source_file": "/Users/alex/Documents/08_MyCrew_Anti/03_Reference_IP/05_Dual-Model_Insights_v1/\ud83d\udd2c CKS_\uc5f0\uad6c\ud504\ub808\uc784\uc6cc\ud06c/\uc5f0\uad6c\uacc4\ud68d\uc11c/\uac80\ud1a0\uc758\uacac_Sonnet.md", "source_location": "L116"}, {"id": "\uc5f0\uad6c\uacc4\ud68d\uc11c_\uac80\ud1a0\uc758\uacac_sonnet_codeblock_6", "label": "code:block6 (\u2461 \uc77c\ubc18\ud654 \uac00\ub2a5\uc131: \ub2e8\uc77c \ud0dc\uc2a4\ud06c \uacb0\uacfc\uac00 \ud0c0 \ub3c4\uba54\uc778\uc5d0 \uc801\uc6a9\ub418\ub294\uc9c0 \ubcc4\ub3c4 \uac80\uc99d \ud544\uc694)", "file_type": "document", "source_file": "/Users/alex/Documents/08_MyCrew_Anti/03_Reference_IP/05_Dual-Model_Insights_v1/\ud83d\udd2c CKS_\uc5f0\uad6c\ud504\ub808\uc784\uc6cc\ud06c/\uc5f0\uad6c\uacc4\ud68d\uc11c/\uac80\ud1a0\uc758\uacac_Sonnet.md", "source_location": "L121"}, {"id": "\uc5f0\uad6c\uacc4\ud68d\uc11c_\uac80\ud1a0\uc758\uacac_sonnet_\uad6c\uc870_\uac1c\uc120_\uc81c\uc548", "label": "\ud83d\udfe2 \uad6c\uc870 \uac1c\uc120 \uc81c\uc548", "file_type": "document", "source_file": "/Users/alex/Documents/08_MyCrew_Anti/03_Reference_IP/05_Dual-Model_Insights_v1/\ud83d\udd2c CKS_\uc5f0\uad6c\ud504\ub808\uc784\uc6cc\ud06c/\uc5f0\uad6c\uacc4\ud68d\uc11c/\uac80\ud1a0\uc758\uacac_Sonnet.md", "source_location": "L129"}, {"id": "\uc5f0\uad6c\uacc4\ud68d\uc11c_\uac80\ud1a0\uc758\uacac_sonnet_codeblock_7", "label": "code:block7 (\ud604\uc7ac:)", "file_type": "document", "source_file": "/Users/alex/Documents/08_MyCrew_Anti/03_Reference_IP/05_Dual-Model_Insights_v1/\ud83d\udd2c CKS_\uc5f0\uad6c\ud504\ub808\uc784\uc6cc\ud06c/\uc5f0\uad6c\uacc4\ud68d\uc11c/\uac80\ud1a0\uc758\uacac_Sonnet.md", "source_location": "L131"}, {"id": "\uc5f0\uad6c\uacc4\ud68d\uc11c_\uac80\ud1a0\uc758\uacac_sonnet_\ud55c_\uc904_\ucd1d\ud3c9", "label": "\ud55c \uc904 \ucd1d\ud3c9", "file_type": "document", "source_file": "/Users/alex/Documents/08_MyCrew_Anti/03_Reference_IP/05_Dual-Model_Insights_v1/\ud83d\udd2c CKS_\uc5f0\uad6c\ud504\ub808\uc784\uc6cc\ud06c/\uc5f0\uad6c\uacc4\ud68d\uc11c/\uac80\ud1a0\uc758\uacac_Sonnet.md", "source_location": "L150"}], "edges": [{"source": "users_alex_documents_08_mycrew_anti_03_reference_ip_05_dual_model_insights_v1_cks_\uc5f0\uad6c\ud504\ub808\uc784\uc6cc\ud06c_\uc5f0\uad6c\uacc4\ud68d\uc11c_\uac80\ud1a0\uc758\uacac_sonnet_md", "target": "\uc5f0\uad6c\uacc4\ud68d\uc11c_\uac80\ud1a0\uc758\uacac_sonnet_\uc5f0\uad6c\uacc4\ud68d\uc11c_\uac80\ud1a0_\uc758\uacac", "relation": "contains", "confidence": "EXTRACTED", "source_file": "/Users/alex/Documents/08_MyCrew_Anti/03_Reference_IP/05_Dual-Model_Insights_v1/\ud83d\udd2c CKS_\uc5f0\uad6c\ud504\ub808\uc784\uc6cc\ud06c/\uc5f0\uad6c\uacc4\ud68d\uc11c/\uac80\ud1a0\uc758\uacac_Sonnet.md", "source_location": "L1", "weight": 1.0}, {"source": "\uc5f0\uad6c\uacc4\ud68d\uc11c_\uac80\ud1a0\uc758\uacac_sonnet_\uc5f0\uad6c\uacc4\ud68d\uc11c_\uac80\ud1a0_\uc758\uacac", "target": "\uc5f0\uad6c\uacc4\ud68d\uc11c_\uac80\ud1a0\uc758\uacac_sonnet_\uc18c\ub137\uc758_\ub300\ud45c\ub2d8_\uc5f0\uad6c\uacc4\ud68d\uc11c_\ub9ac\ubdf0", "relation": "contains", "confidence": "EXTRACTED", "source_file": "/Users/alex/Documents/08_MyCrew_Anti/03_Reference_IP/05_Dual-Model_Insights_v1/\ud83d\udd2c CKS_\uc5f0\uad6c\ud504\ub808\uc784\uc6cc\ud06c/\uc5f0\uad6c\uacc4\ud68d\uc11c/\uac80\ud1a0\uc758\uacac_Sonnet.md", "source_location": "L2", "weight": 1.0}, {"source": "\uc5f0\uad6c\uacc4\ud68d\uc11c_\uac80\ud1a0\uc758\uacac_sonnet_\uc5f0\uad6c\uacc4\ud68d\uc11c_\uac80\ud1a0_\uc758\uacac", "target": "\uc5f0\uad6c\uacc4\ud68d\uc11c_\uac80\ud1a0\uc758\uacac_sonnet_\uc798_\ub41c_\ubd80\ubd84", "relation": "contains", "confidence": "EXTRACTED", "source_file": "/Users/alex/Documents/08_MyCrew_Anti/03_Reference_IP/05_Dual-Model_Insights_v1/\ud83d\udd2c CKS_\uc5f0\uad6c\ud504\ub808\uc784\uc6cc\ud06c/\uc5f0\uad6c\uacc4\ud68d\uc11c/\uac80\ud1a0\uc758\uacac_Sonnet.md", "source_location": "L11", "weight": 1.0}, {"source": "\uc5f0\uad6c\uacc4\ud68d\uc11c_\uac80\ud1a0\uc758\uacac_sonnet_\uc5f0\uad6c\uacc4\ud68d\uc11c_\uac80\ud1a0_\uc758\uacac", "target": "\uc5f0\uad6c\uacc4\ud68d\uc11c_\uac80\ud1a0\uc758\uacac_sonnet_\uc218\uc815_\ud544\uc218_\uce58\uba85\uc801_\ubb38\uc81c_3\uac1c", "relation": "contains", "confidence": "EXTRACTED", "source_file": "/Users/alex/Documents/08_MyCrew_Anti/03_Reference_IP/05_Dual-Model_Insights_v1/\ud83d\udd2c CKS_\uc5f0\uad6c\ud504\ub808\uc784\uc6cc\ud06c/\uc5f0\uad6c\uacc4\ud68d\uc11c/\uac80\ud1a0\uc758\uacac_Sonnet.md", "source_location": "L19", "weight": 1.0}, {"source": "\uc5f0\uad6c\uacc4\ud68d\uc11c_\uac80\ud1a0\uc758\uacac_sonnet_\uc218\uc815_\ud544\uc218_\uce58\uba85\uc801_\ubb38\uc81c_3\uac1c", "target": "\uc5f0\uad6c\uacc4\ud68d\uc11c_\uac80\ud1a0\uc758\uacac_sonnet_1_\ud3c9\uac00\uc790_\uc21c\ud658_\ud3b8\ud5a5_circular_bias", "relation": "contains", "confidence": "EXTRACTED", "source_file": "/Users/alex/Documents/08_MyCrew_Anti/03_Reference_IP/05_Dual-Model_Insights_v1/\ud83d\udd2c CKS_\uc5f0\uad6c\ud504\ub808\uc784\uc6cc\ud06c/\uc5f0\uad6c\uacc4\ud68d\uc11c/\uac80\ud1a0\uc758\uacac_Sonnet.md", "source_location": "L23", "weight": 1.0}, {"source": "\uc5f0\uad6c\uacc4\ud68d\uc11c_\uac80\ud1a0\uc758\uacac_sonnet_1_\ud3c9\uac00\uc790_\uc21c\ud658_\ud3b8\ud5a5_circular_bias", "target": "\uc5f0\uad6c\uacc4\ud68d\uc11c_\uac80\ud1a0\uc758\uacac_sonnet_codeblock_1", "relation": "contains", "confidence": "EXTRACTED", "source_file": "/Users/alex/Documents/08_MyCrew_Anti/03_Reference_IP/05_Dual-Model_Insights_v1/\ud83d\udd2c CKS_\uc5f0\uad6c\ud504\ub808\uc784\uc6cc\ud06c/\uc5f0\uad6c\uacc4\ud68d\uc11c/\uac80\ud1a0\uc758\uacac_Sonnet.md", "source_location": "L27", "weight": 1.0}, {"source": "\uc5f0\uad6c\uacc4\ud68d\uc11c_\uac80\ud1a0\uc758\uacac_sonnet_\uc218\uc815_\ud544\uc218_\uce58\uba85\uc801_\ubb38\uc81c_3\uac1c", "target": "\uc5f0\uad6c\uacc4\ud68d\uc11c_\uac80\ud1a0\uc758\uacac_sonnet_2_phase_4_\uba54\ud0c0_\ud504\ub86c\ud504\ud305\uc758_\uc624\uc5fc_\uac00\ub2a5\uc131_\ubbf8\uc124\uba85", "relation": "contains", "confidence": "EXTRACTED", "source_file": "/Users/alex/Documents/08_MyCrew_Anti/03_Reference_IP/05_Dual-Model_Insights_v1/\ud83d\udd2c CKS_\uc5f0\uad6c\ud504\ub808\uc784\uc6cc\ud06c/\uc5f0\uad6c\uacc4\ud68d\uc11c/\uac80\ud1a0\uc758\uacac_Sonnet.md", "source_location": "L40", "weight": 1.0}, {"source": "\uc5f0\uad6c\uacc4\ud68d\uc11c_\uac80\ud1a0\uc758\uacac_sonnet_2_phase_4_\uba54\ud0c0_\ud504\ub86c\ud504\ud305\uc758_\uc624\uc5fc_\uac00\ub2a5\uc131_\ubbf8\uc124\uba85", "target": "\uc5f0\uad6c\uacc4\ud68d\uc11c_\uac80\ud1a0\uc758\uacac_sonnet_codeblock_2", "relation": "contains", "confidence": "EXTRACTED", "source_file": "/Users/alex/Documents/08_MyCrew_Anti/03_Reference_IP/05_Dual-Model_Insights_v1/\ud83d\udd2c CKS_\uc5f0\uad6c\ud504\ub808\uc784\uc6cc\ud06c/\uc5f0\uad6c\uacc4\ud68d\uc11c/\uac80\ud1a0\uc758\uacac_Sonnet.md", "source_location": "L44", "weight": 1.0}, {"source": "\uc5f0\uad6c\uacc4\ud68d\uc11c_\uac80\ud1a0\uc758\uacac_sonnet_\uc218\uc815_\ud544\uc218_\uce58\uba85\uc801_\ubb38\uc81c_3\uac1c", "target": "\uc5f0\uad6c\uacc4\ud68d\uc11c_\uac80\ud1a0\uc758\uacac_sonnet_3_ksi_\uacf5\uc2dd_\ubbf8\uc815\uc758", "relation": "contains", "confidence": "EXTRACTED", "source_file": "/Users/alex/Documents/08_MyCrew_Anti/03_Reference_IP/05_Dual-Model_Insights_v1/\ud83d\udd2c CKS_\uc5f0\uad6c\ud504\ub808\uc784\uc6cc\ud06c/\uc5f0\uad6c\uacc4\ud68d\uc11c/\uac80\ud1a0\uc758\uacac_Sonnet.md", "source_location": "L56", "weight": 1.0}, {"source": "\uc5f0\uad6c\uacc4\ud68d\uc11c_\uac80\ud1a0\uc758\uacac_sonnet_3_ksi_\uacf5\uc2dd_\ubbf8\uc815\uc758", "target": "\uc5f0\uad6c\uacc4\ud68d\uc11c_\uac80\ud1a0\uc758\uacac_sonnet_codeblock_3", "relation": "contains", "confidence": "EXTRACTED", "source_file": "/Users/alex/Documents/08_MyCrew_Anti/03_Reference_IP/05_Dual-Model_Insights_v1/\ud83d\udd2c CKS_\uc5f0\uad6c\ud504\ub808\uc784\uc6cc\ud06c/\uc5f0\uad6c\uacc4\ud68d\uc11c/\uac80\ud1a0\uc758\uacac_Sonnet.md", "source_location": "L61", "weight": 1.0}, {"source": "\uc5f0\uad6c\uacc4\ud68d\uc11c_\uac80\ud1a0\uc758\uacac_sonnet_\uc5f0\uad6c\uacc4\ud68d\uc11c_\uac80\ud1a0_\uc758\uacac", "target": "\uc5f0\uad6c\uacc4\ud68d\uc11c_\uac80\ud1a0\uc758\uacac_sonnet_\ubcf4\uc644_\uad8c\uc7a5_4\uac1c", "relation": "contains", "confidence": "EXTRACTED", "source_file": "/Users/alex/Documents/08_MyCrew_Anti/03_Reference_IP/05_Dual-Model_Insights_v1/\ud83d\udd2c CKS_\uc5f0\uad6c\ud504\ub808\uc784\uc6cc\ud06c/\uc5f0\uad6c\uacc4\ud68d\uc11c/\uac80\ud1a0\uc758\uacac_Sonnet.md", "source_location": "L73", "weight": 1.0}, {"source": "\uc5f0\uad6c\uacc4\ud68d\uc11c_\uac80\ud1a0\uc758\uacac_sonnet_\ubcf4\uc644_\uad8c\uc7a5_4\uac1c", "target": "\uc5f0\uad6c\uacc4\ud68d\uc11c_\uac80\ud1a0\uc758\uacac_sonnet_4_research_question_rq_\ubd80\uc7ac", "relation": "contains", "confidence": "EXTRACTED", "source_file": "/Users/alex/Documents/08_MyCrew_Anti/03_Reference_IP/05_Dual-Model_Insights_v1/\ud83d\udd2c CKS_\uc5f0\uad6c\ud504\ub808\uc784\uc6cc\ud06c/\uc5f0\uad6c\uacc4\ud68d\uc11c/\uac80\ud1a0\uc758\uacac_Sonnet.md", "source_location": "L75", "weight": 1.0}, {"source": "\uc5f0\uad6c\uacc4\ud68d\uc11c_\uac80\ud1a0\uc758\uacac_sonnet_4_research_question_rq_\ubd80\uc7ac", "target": "\uc5f0\uad6c\uacc4\ud68d\uc11c_\uac80\ud1a0\uc758\uacac_sonnet_codeblock_4", "relation": "contains", "confidence": "EXTRACTED", "source_file": "/Users/alex/Documents/08_MyCrew_Anti/03_Reference_IP/05_Dual-Model_Insights_v1/\ud83d\udd2c CKS_\uc5f0\uad6c\ud504\ub808\uc784\uc6cc\ud06c/\uc5f0\uad6c\uacc4\ud68d\uc11c/\uac80\ud1a0\uc758\uacac_Sonnet.md", "source_location": "L80", "weight": 1.0}, {"source": "\uc5f0\uad6c\uacc4\ud68d\uc11c_\uac80\ud1a0\uc758\uacac_sonnet_\ubcf4\uc644_\uad8c\uc7a5_4\uac1c", "target": "\uc5f0\uad6c\uacc4\ud68d\uc11c_\uac80\ud1a0\uc758\uacac_sonnet_5_\uad00\ub828_\uc5f0\uad6c_related_work_\uc804\ubb34", "relation": "contains", "confidence": "EXTRACTED", "source_file": "/Users/alex/Documents/08_MyCrew_Anti/03_Reference_IP/05_Dual-Model_Insights_v1/\ud83d\udd2c CKS_\uc5f0\uad6c\ud504\ub808\uc784\uc6cc\ud06c/\uc5f0\uad6c\uacc4\ud68d\uc11c/\uac80\ud1a0\uc758\uacac_Sonnet.md", "source_location": "L93", "weight": 1.0}, {"source": "\uc5f0\uad6c\uacc4\ud68d\uc11c_\uac80\ud1a0\uc758\uacac_sonnet_\ubcf4\uc644_\uad8c\uc7a5_4\uac1c", "target": "\uc5f0\uad6c\uacc4\ud68d\uc11c_\uac80\ud1a0\uc758\uacac_sonnet_6_\ud30c\uc77c\ub7ff_\ub370\uc774\ud130_\ubbf8\uc5b8\uae09", "relation": "contains", "confidence": "EXTRACTED", "source_file": "/Users/alex/Documents/08_MyCrew_Anti/03_Reference_IP/05_Dual-Model_Insights_v1/\ud83d\udd2c CKS_\uc5f0\uad6c\ud504\ub808\uc784\uc6cc\ud06c/\uc5f0\uad6c\uacc4\ud68d\uc11c/\uac80\ud1a0\uc758\uacac_Sonnet.md", "source_location": "L105", "weight": 1.0}, {"source": "\uc5f0\uad6c\uacc4\ud68d\uc11c_\uac80\ud1a0\uc758\uacac_sonnet_6_\ud30c\uc77c\ub7ff_\ub370\uc774\ud130_\ubbf8\uc5b8\uae09", "target": "\uc5f0\uad6c\uacc4\ud68d\uc11c_\uac80\ud1a0\uc758\uacac_sonnet_codeblock_5", "relation": "contains", "confidence": "EXTRACTED", "source_file": "/Users/alex/Documents/08_MyCrew_Anti/03_Reference_IP/05_Dual-Model_Insights_v1/\ud83d\udd2c CKS_\uc5f0\uad6c\ud504\ub808\uc784\uc6cc\ud06c/\uc5f0\uad6c\uacc4\ud68d\uc11c/\uac80\ud1a0\uc758\uacac_Sonnet.md", "source_location": "L108", "weight": 1.0}, {"source": "\uc5f0\uad6c\uacc4\ud68d\uc11c_\uac80\ud1a0\uc758\uacac_sonnet_\ubcf4\uc644_\uad8c\uc7a5_4\uac1c", "target": "\uc5f0\uad6c\uacc4\ud68d\uc11c_\uac80\ud1a0\uc758\uacac_sonnet_7_\ud55c\uacc4\uc810_\ucd94\uac00_\ud544\uc694", "relation": "contains", "confidence": "EXTRACTED", "source_file": "/Users/alex/Documents/08_MyCrew_Anti/03_Reference_IP/05_Dual-Model_Insights_v1/\ud83d\udd2c CKS_\uc5f0\uad6c\ud504\ub808\uc784\uc6cc\ud06c/\uc5f0\uad6c\uacc4\ud68d\uc11c/\uac80\ud1a0\uc758\uacac_Sonnet.md", "source_location": "L116", "weight": 1.0}, {"source": "\uc5f0\uad6c\uacc4\ud68d\uc11c_\uac80\ud1a0\uc758\uacac_sonnet_7_\ud55c\uacc4\uc810_\ucd94\uac00_\ud544\uc694", "target": "\uc5f0\uad6c\uacc4\ud68d\uc11c_\uac80\ud1a0\uc758\uacac_sonnet_codeblock_6", "relation": "contains", "confidence": "EXTRACTED", "source_file": "/Users/alex/Documents/08_MyCrew_Anti/03_Reference_IP/05_Dual-Model_Insights_v1/\ud83d\udd2c CKS_\uc5f0\uad6c\ud504\ub808\uc784\uc6cc\ud06c/\uc5f0\uad6c\uacc4\ud68d\uc11c/\uac80\ud1a0\uc758\uacac_Sonnet.md", "source_location": "L121", "weight": 1.0}, {"source": "\uc5f0\uad6c\uacc4\ud68d\uc11c_\uac80\ud1a0\uc758\uacac_sonnet_\uc5f0\uad6c\uacc4\ud68d\uc11c_\uac80\ud1a0_\uc758\uacac", "target": "\uc5f0\uad6c\uacc4\ud68d\uc11c_\uac80\ud1a0\uc758\uacac_sonnet_\uad6c\uc870_\uac1c\uc120_\uc81c\uc548", "relation": "contains", "confidence": "EXTRACTED", "source_file": "/Users/alex/Documents/08_MyCrew_Anti/03_Reference_IP/05_Dual-Model_Insights_v1/\ud83d\udd2c CKS_\uc5f0\uad6c\ud504\ub808\uc784\uc6cc\ud06c/\uc5f0\uad6c\uacc4\ud68d\uc11c/\uac80\ud1a0\uc758\uacac_Sonnet.md", "source_location": "L129", "weight": 1.0}, {"source": "\uc5f0\uad6c\uacc4\ud68d\uc11c_\uac80\ud1a0\uc758\uacac_sonnet_\uad6c\uc870_\uac1c\uc120_\uc81c\uc548", "target": "\uc5f0\uad6c\uacc4\ud68d\uc11c_\uac80\ud1a0\uc758\uacac_sonnet_codeblock_7", "relation": "contains", "confidence": "EXTRACTED", "source_file": "/Users/alex/Documents/08_MyCrew_Anti/03_Reference_IP/05_Dual-Model_Insights_v1/\ud83d\udd2c CKS_\uc5f0\uad6c\ud504\ub808\uc784\uc6cc\ud06c/\uc5f0\uad6c\uacc4\ud68d\uc11c/\uac80\ud1a0\uc758\uacac_Sonnet.md", "source_location": "L131", "weight": 1.0}, {"source": "\uc5f0\uad6c\uacc4\ud68d\uc11c_\uac80\ud1a0\uc758\uacac_sonnet_\uc5f0\uad6c\uacc4\ud68d\uc11c_\uac80\ud1a0_\uc758\uacac", "target": "\uc5f0\uad6c\uacc4\ud68d\uc11c_\uac80\ud1a0\uc758\uacac_sonnet_\ud55c_\uc904_\ucd1d\ud3c9", "relation": "contains", "confidence": "EXTRACTED", "source_file": "/Users/alex/Documents/08_MyCrew_Anti/03_Reference_IP/05_Dual-Model_Insights_v1/\ud83d\udd2c CKS_\uc5f0\uad6c\ud504\ub808\uc784\uc6cc\ud06c/\uc5f0\uad6c\uacc4\ud68d\uc11c/\uac80\ud1a0\uc758\uacac_Sonnet.md", "source_location": "L150", "weight": 1.0}], "input_tokens": 0, "output_tokens": 0}